[
  {
    "id": 1,
    "title": "Book Your Appointment",
    "description": "Video-call us or Walk-in "
  },
  {
    "id": 2,
    "title": "Our History",
    "description": "We trace our lineage to two families of Banaras manufacturing and trade from the 1820s"
  },
  {
    "id": 263,
    "title": "Book Your Appointment",
    "description": "Video-call us or Walk-in "
  },
  {
    "id": 264,
    "title": "Our History",
    "description": "We trace our lineage to two families of Banaras manufacturing and trade from the 1820s"
  }
]