[
  {
    "id": 241,
    "amount": "240.00",
    "payment_status": "COMPLETED",
    "order_uid": "37L48393WB2019611",
    "paypal_response": {
      "id": "37L48393WB2019611",
      "links": [
        {
          "rel": "self",
          "href": "https://api.sandbox.paypal.com/v2/checkout/orders/37L48393WB2019611",
          "method": "GET"
        }
      ],
      "payer": {
        "name": {
          "surname": "Doe",
          "given_name": "John"
        },
        "address": {
          "country_code": "US"
        },
        "payer_id": "9FRBXH62VVGQE",
        "email_address": "sb-cycty38175316@personal.example.com"
      },
      "status": "COMPLETED",
      "payment_source": {
        "paypal": {
          "name": {
            "surname": "Doe",
            "given_name": "John"
          },
          "address": {
            "country_code": "US"
          },
          "account_id": "9FRBXH62VVGQE",
          "email_address": "sb-cycty38175316@personal.example.com",
          "account_status": "VERIFIED",
          "app_switch_eligibility": false
        }
      },
      "purchase_units": [
        {
          "payments": {
            "captures": [
              {
                "id": "6PL90190349762709",
                "links": [
                  {
                    "rel": "self",
                    "href": "https://api.sandbox.paypal.com/v2/payments/captures/6PL90190349762709",
                    "method": "GET"
                  },
                  {
                    "rel": "refund",
                    "href": "https://api.sandbox.paypal.com/v2/payments/captures/6PL90190349762709/refund",
                    "method": "POST"
                  },
                  {
                    "rel": "up",
                    "href": "https://api.sandbox.paypal.com/v2/checkout/orders/37L48393WB2019611",
                    "method": "GET"
                  }
                ],
                "amount": {
                  "value": "240.00",
                  "currency_code": "USD"
                },
                "status": "COMPLETED",
                "create_time": "2025-03-19T11:42:27Z",
                "update_time": "2025-03-19T11:42:27Z",
                "final_capture": true,
                "seller_protection": {
                  "status": "ELIGIBLE",
                  "dispute_categories": [
                    "ITEM_NOT_RECEIVED",
                    "UNAUTHORIZED_TRANSACTION"
                  ]
                },
                "seller_receivable_breakdown": {
                  "net_amount": {
                    "value": "228.60",
                    "currency_code": "USD"
                  },
                  "paypal_fee": {
                    "value": "11.40",
                    "currency_code": "USD"
                  },
                  "gross_amount": {
                    "value": "240.00",
                    "currency_code": "USD"
                  }
                }
              }
            ]
          },
          "shipping": {
            "name": {
              "full_name": "John Doe"
            },
            "address": {
              "postal_code": "95131",
              "admin_area_1": "CA",
              "admin_area_2": "San Jose",
              "country_code": "US",
              "address_line_1": "1 Main St"
            }
          },
          "reference_id": "default"
        }
      ]
    }
  },
  {
    "id": 245,
    "amount": "228.00",
    "payment_status": "COMPLETED",
    "order_uid": "72V17630MC809893J",
    "paypal_response": {
      "id": "72V17630MC809893J",
      "links": [
        {
          "rel": "self",
          "href": "https://api.sandbox.paypal.com/v2/checkout/orders/72V17630MC809893J",
          "method": "GET"
        }
      ],
      "payer": {
        "name": {
          "surname": "Doe",
          "given_name": "John"
        },
        "address": {
          "country_code": "US"
        },
        "payer_id": "9FRBXH62VVGQE",
        "email_address": "sb-cycty38175316@personal.example.com"
      },
      "status": "COMPLETED",
      "payment_source": {
        "paypal": {
          "name": {
            "surname": "Doe",
            "given_name": "John"
          },
          "address": {
            "country_code": "US"
          },
          "account_id": "9FRBXH62VVGQE",
          "email_address": "sb-cycty38175316@personal.example.com",
          "account_status": "VERIFIED",
          "app_switch_eligibility": false
        }
      },
      "purchase_units": [
        {
          "payments": {
            "captures": [
              {
                "id": "52F33995X94514100",
                "links": [
                  {
                    "rel": "self",
                    "href": "https://api.sandbox.paypal.com/v2/payments/captures/52F33995X94514100",
                    "method": "GET"
                  },
                  {
                    "rel": "refund",
                    "href": "https://api.sandbox.paypal.com/v2/payments/captures/52F33995X94514100/refund",
                    "method": "POST"
                  },
                  {
                    "rel": "up",
                    "href": "https://api.sandbox.paypal.com/v2/checkout/orders/72V17630MC809893J",
                    "method": "GET"
                  }
                ],
                "amount": {
                  "value": "228.00",
                  "currency_code": "USD"
                },
                "status": "COMPLETED",
                "create_time": "2025-03-19T11:48:34Z",
                "update_time": "2025-03-19T11:48:34Z",
                "final_capture": true,
                "seller_protection": {
                  "status": "ELIGIBLE",
                  "dispute_categories": [
                    "ITEM_NOT_RECEIVED",
                    "UNAUTHORIZED_TRANSACTION"
                  ]
                },
                "seller_receivable_breakdown": {
                  "net_amount": {
                    "value": "217.16",
                    "currency_code": "USD"
                  },
                  "paypal_fee": {
                    "value": "10.84",
                    "currency_code": "USD"
                  },
                  "gross_amount": {
                    "value": "228.00",
                    "currency_code": "USD"
                  }
                }
              }
            ]
          },
          "shipping": {
            "name": {
              "full_name": "John Doe"
            },
            "address": {
              "postal_code": "95131",
              "admin_area_1": "CA",
              "admin_area_2": "San Jose",
              "country_code": "US",
              "address_line_1": "1 Main St"
            }
          },
          "reference_id": "default"
        }
      ]
    }
  },
  {
    "id": 246,
    "amount": "228.00",
    "payment_status": "COMPLETED",
    "order_uid": "72V17630MC809893J",
    "paypal_response": {
      "id": "72V17630MC809893J",
      "links": [
        {
          "rel": "self",
          "href": "https://api.sandbox.paypal.com/v2/checkout/orders/72V17630MC809893J",
          "method": "GET"
        }
      ],
      "payer": {
        "name": {
          "surname": "Doe",
          "given_name": "John"
        },
        "address": {
          "country_code": "US"
        },
        "payer_id": "9FRBXH62VVGQE",
        "email_address": "sb-cycty38175316@personal.example.com"
      },
      "status": "COMPLETED",
      "payment_source": {
        "paypal": {
          "name": {
            "surname": "Doe",
            "given_name": "John"
          },
          "address": {
            "country_code": "US"
          },
          "account_id": "9FRBXH62VVGQE",
          "email_address": "sb-cycty38175316@personal.example.com",
          "account_status": "VERIFIED",
          "app_switch_eligibility": false
        }
      },
      "purchase_units": [
        {
          "payments": {
            "captures": [
              {
                "id": "52F33995X94514100",
                "links": [
                  {
                    "rel": "self",
                    "href": "https://api.sandbox.paypal.com/v2/payments/captures/52F33995X94514100",
                    "method": "GET"
                  },
                  {
                    "rel": "refund",
                    "href": "https://api.sandbox.paypal.com/v2/payments/captures/52F33995X94514100/refund",
                    "method": "POST"
                  },
                  {
                    "rel": "up",
                    "href": "https://api.sandbox.paypal.com/v2/checkout/orders/72V17630MC809893J",
                    "method": "GET"
                  }
                ],
                "amount": {
                  "value": "228.00",
                  "currency_code": "USD"
                },
                "status": "COMPLETED",
                "create_time": "2025-03-19T11:48:34Z",
                "update_time": "2025-03-19T11:48:34Z",
                "final_capture": true,
                "seller_protection": {
                  "status": "ELIGIBLE",
                  "dispute_categories": [
                    "ITEM_NOT_RECEIVED",
                    "UNAUTHORIZED_TRANSACTION"
                  ]
                },
                "seller_receivable_breakdown": {
                  "net_amount": {
                    "value": "217.16",
                    "currency_code": "USD"
                  },
                  "paypal_fee": {
                    "value": "10.84",
                    "currency_code": "USD"
                  },
                  "gross_amount": {
                    "value": "228.00",
                    "currency_code": "USD"
                  }
                }
              }
            ]
          },
          "shipping": {
            "name": {
              "full_name": "John Doe"
            },
            "address": {
              "postal_code": "95131",
              "admin_area_1": "CA",
              "admin_area_2": "San Jose",
              "country_code": "US",
              "address_line_1": "1 Main St"
            }
          },
          "reference_id": "default"
        }
      ]
    }
  },
  {
    "id": 249,
    "amount": "54.00",
    "payment_status": "COMPLETED",
    "order_uid": "2F245326LB102532S",
    "paypal_response": {
      "id": "2F245326LB102532S",
      "links": [
        {
          "rel": "self",
          "href": "https://api.sandbox.paypal.com/v2/checkout/orders/2F245326LB102532S",
          "method": "GET"
        }
      ],
      "payer": {
        "name": {
          "surname": "Doe",
          "given_name": "John"
        },
        "address": {
          "country_code": "US"
        },
        "payer_id": "9FRBXH62VVGQE",
        "email_address": "sb-cycty38175316@personal.example.com"
      },
      "status": "COMPLETED",
      "payment_source": {
        "paypal": {
          "name": {
            "surname": "Doe",
            "given_name": "John"
          },
          "address": {
            "country_code": "US"
          },
          "account_id": "9FRBXH62VVGQE",
          "email_address": "sb-cycty38175316@personal.example.com",
          "account_status": "VERIFIED",
          "app_switch_eligibility": false
        }
      },
      "purchase_units": [
        {
          "payments": {
            "captures": [
              {
                "id": "4HY05117JE559424H",
                "links": [
                  {
                    "rel": "self",
                    "href": "https://api.sandbox.paypal.com/v2/payments/captures/4HY05117JE559424H",
                    "method": "GET"
                  },
                  {
                    "rel": "refund",
                    "href": "https://api.sandbox.paypal.com/v2/payments/captures/4HY05117JE559424H/refund",
                    "method": "POST"
                  },
                  {
                    "rel": "up",
                    "href": "https://api.sandbox.paypal.com/v2/checkout/orders/2F245326LB102532S",
                    "method": "GET"
                  }
                ],
                "amount": {
                  "value": "54.00",
                  "currency_code": "USD"
                },
                "status": "COMPLETED",
                "create_time": "2025-03-23T15:11:39Z",
                "update_time": "2025-03-23T15:11:39Z",
                "final_capture": true,
                "seller_protection": {
                  "status": "ELIGIBLE",
                  "dispute_categories": [
                    "ITEM_NOT_RECEIVED",
                    "UNAUTHORIZED_TRANSACTION"
                  ]
                },
                "seller_receivable_breakdown": {
                  "net_amount": {
                    "value": "51.16",
                    "currency_code": "USD"
                  },
                  "paypal_fee": {
                    "value": "2.84",
                    "currency_code": "USD"
                  },
                  "gross_amount": {
                    "value": "54.00",
                    "currency_code": "USD"
                  }
                }
              }
            ]
          },
          "shipping": {
            "name": {
              "full_name": "John Doe"
            },
            "address": {
              "postal_code": "95131",
              "admin_area_1": "CA",
              "admin_area_2": "San Jose",
              "country_code": "US",
              "address_line_1": "1 Main St"
            }
          },
          "reference_id": "default"
        }
      ]
    }
  },
  {
    "id": 250,
    "amount": "54.00",
    "payment_status": "COMPLETED",
    "order_uid": "2F245326LB102532S",
    "paypal_response": {
      "id": "2F245326LB102532S",
      "links": [
        {
          "rel": "self",
          "href": "https://api.sandbox.paypal.com/v2/checkout/orders/2F245326LB102532S",
          "method": "GET"
        }
      ],
      "payer": {
        "name": {
          "surname": "Doe",
          "given_name": "John"
        },
        "address": {
          "country_code": "US"
        },
        "payer_id": "9FRBXH62VVGQE",
        "email_address": "sb-cycty38175316@personal.example.com"
      },
      "status": "COMPLETED",
      "payment_source": {
        "paypal": {
          "name": {
            "surname": "Doe",
            "given_name": "John"
          },
          "address": {
            "country_code": "US"
          },
          "account_id": "9FRBXH62VVGQE",
          "email_address": "sb-cycty38175316@personal.example.com",
          "account_status": "VERIFIED",
          "app_switch_eligibility": false
        }
      },
      "purchase_units": [
        {
          "payments": {
            "captures": [
              {
                "id": "4HY05117JE559424H",
                "links": [
                  {
                    "rel": "self",
                    "href": "https://api.sandbox.paypal.com/v2/payments/captures/4HY05117JE559424H",
                    "method": "GET"
                  },
                  {
                    "rel": "refund",
                    "href": "https://api.sandbox.paypal.com/v2/payments/captures/4HY05117JE559424H/refund",
                    "method": "POST"
                  },
                  {
                    "rel": "up",
                    "href": "https://api.sandbox.paypal.com/v2/checkout/orders/2F245326LB102532S",
                    "method": "GET"
                  }
                ],
                "amount": {
                  "value": "54.00",
                  "currency_code": "USD"
                },
                "status": "COMPLETED",
                "create_time": "2025-03-23T15:11:39Z",
                "update_time": "2025-03-23T15:11:39Z",
                "final_capture": true,
                "seller_protection": {
                  "status": "ELIGIBLE",
                  "dispute_categories": [
                    "ITEM_NOT_RECEIVED",
                    "UNAUTHORIZED_TRANSACTION"
                  ]
                },
                "seller_receivable_breakdown": {
                  "net_amount": {
                    "value": "51.16",
                    "currency_code": "USD"
                  },
                  "paypal_fee": {
                    "value": "2.84",
                    "currency_code": "USD"
                  },
                  "gross_amount": {
                    "value": "54.00",
                    "currency_code": "USD"
                  }
                }
              }
            ]
          },
          "shipping": {
            "name": {
              "full_name": "John Doe"
            },
            "address": {
              "postal_code": "95131",
              "admin_area_1": "CA",
              "admin_area_2": "San Jose",
              "country_code": "US",
              "address_line_1": "1 Main St"
            }
          },
          "reference_id": "default"
        }
      ]
    }
  },
  {
    "id": 258,
    "amount": "240.00",
    "payment_status": "COMPLETED",
    "order_uid": "37L48393WB2019611",
    "paypal_response": {
      "id": "37L48393WB2019611",
      "links": [
        {
          "rel": "self",
          "href": "https://api.sandbox.paypal.com/v2/checkout/orders/37L48393WB2019611",
          "method": "GET"
        }
      ],
      "payer": {
        "name": {
          "surname": "Doe",
          "given_name": "John"
        },
        "address": {
          "country_code": "US"
        },
        "payer_id": "9FRBXH62VVGQE",
        "email_address": "sb-cycty38175316@personal.example.com"
      },
      "status": "COMPLETED",
      "payment_source": {
        "paypal": {
          "name": {
            "surname": "Doe",
            "given_name": "John"
          },
          "address": {
            "country_code": "US"
          },
          "account_id": "9FRBXH62VVGQE",
          "email_address": "sb-cycty38175316@personal.example.com",
          "account_status": "VERIFIED",
          "app_switch_eligibility": false
        }
      },
      "purchase_units": [
        {
          "payments": {
            "captures": [
              {
                "id": "6PL90190349762709",
                "links": [
                  {
                    "rel": "self",
                    "href": "https://api.sandbox.paypal.com/v2/payments/captures/6PL90190349762709",
                    "method": "GET"
                  },
                  {
                    "rel": "refund",
                    "href": "https://api.sandbox.paypal.com/v2/payments/captures/6PL90190349762709/refund",
                    "method": "POST"
                  },
                  {
                    "rel": "up",
                    "href": "https://api.sandbox.paypal.com/v2/checkout/orders/37L48393WB2019611",
                    "method": "GET"
                  }
                ],
                "amount": {
                  "value": "240.00",
                  "currency_code": "USD"
                },
                "status": "COMPLETED",
                "create_time": "2025-03-19T11:42:27Z",
                "update_time": "2025-03-19T11:42:27Z",
                "final_capture": true,
                "seller_protection": {
                  "status": "ELIGIBLE",
                  "dispute_categories": [
                    "ITEM_NOT_RECEIVED",
                    "UNAUTHORIZED_TRANSACTION"
                  ]
                },
                "seller_receivable_breakdown": {
                  "net_amount": {
                    "value": "228.60",
                    "currency_code": "USD"
                  },
                  "paypal_fee": {
                    "value": "11.40",
                    "currency_code": "USD"
                  },
                  "gross_amount": {
                    "value": "240.00",
                    "currency_code": "USD"
                  }
                }
              }
            ]
          },
          "shipping": {
            "name": {
              "full_name": "John Doe"
            },
            "address": {
              "postal_code": "95131",
              "admin_area_1": "CA",
              "admin_area_2": "San Jose",
              "country_code": "US",
              "address_line_1": "1 Main St"
            }
          },
          "reference_id": "default"
        }
      ]
    }
  },
  {
    "id": 259,
    "amount": "1114.80",
    "payment_status": "INITIATED",
    "order_uid": "1RX041597E716911P",
    "paypal_response": null
  },
  {
    "id": 260,
    "amount": "1114.80",
    "payment_status": "INITIATED",
    "order_uid": "1RX041597E716911P",
    "paypal_response": null
  },
  {
    "id": 261,
    "amount": "1114.80",
    "payment_status": "INITIATED",
    "order_uid": "4XC09803AG984780X",
    "paypal_response": null
  },
  {
    "id": 262,
    "amount": "1114.80",
    "payment_status": "INITIATED",
    "order_uid": "4XC09803AG984780X",
    "paypal_response": null
  },
  {
    "id": 263,
    "amount": "1114.80",
    "payment_status": "INITIATED",
    "order_uid": "3E063321XN6884926",
    "paypal_response": null
  },
  {
    "id": 264,
    "amount": "1114.80",
    "payment_status": "INITIATED",
    "order_uid": "3E063321XN6884926",
    "paypal_response": null
  },
  {
    "id": 265,
    "amount": "1114.80",
    "payment_status": "INITIATED",
    "order_uid": "3NP835026H972970S",
    "paypal_response": null
  },
  {
    "id": 266,
    "amount": "1114.80",
    "payment_status": "INITIATED",
    "order_uid": "3NP835026H972970S",
    "paypal_response": null
  },
  {
    "id": 267,
    "amount": "1114.80",
    "payment_status": "INITIATED",
    "order_uid": "6SM45777YF907712Y",
    "paypal_response": null
  },
  {
    "id": 268,
    "amount": "1114.80",
    "payment_status": "INITIATED",
    "order_uid": "6SM45777YF907712Y",
    "paypal_response": null
  },
  {
    "id": 269,
    "amount": "1114.80",
    "payment_status": "INITIATED",
    "order_uid": "856057543D507421N",
    "paypal_response": null
  },
  {
    "id": 270,
    "amount": "1114.80",
    "payment_status": "INITIATED",
    "order_uid": "856057543D507421N",
    "paypal_response": null
  },
  {
    "id": 271,
    "amount": "1114.80",
    "payment_status": "INITIATED",
    "order_uid": "3R333555JN1914606",
    "paypal_response": null
  },
  {
    "id": 272,
    "amount": "1114.80",
    "payment_status": "INITIATED",
    "order_uid": "3R333555JN1914606",
    "paypal_response": null
  },
  {
    "id": 273,
    "amount": "1114.80",
    "payment_status": "INITIATED",
    "order_uid": "0GJ95989XY3850032",
    "paypal_response": null
  },
  {
    "id": 274,
    "amount": "1114.80",
    "payment_status": "INITIATED",
    "order_uid": "0GJ95989XY3850032",
    "paypal_response": null
  },
  {
    "id": 275,
    "amount": "1114.80",
    "payment_status": "INITIATED",
    "order_uid": "41U9486466964404M",
    "paypal_response": null
  },
  {
    "id": 276,
    "amount": "1114.80",
    "payment_status": "INITIATED",
    "order_uid": "41U9486466964404M",
    "paypal_response": null
  },
  {
    "id": 277,
    "amount": "1114.80",
    "payment_status": "INITIATED",
    "order_uid": "64J86604JG8996934",
    "paypal_response": null
  },
  {
    "id": 278,
    "amount": "1114.80",
    "payment_status": "INITIATED",
    "order_uid": "64J86604JG8996934",
    "paypal_response": null
  },
  {
    "id": 279,
    "amount": "1114.80",
    "payment_status": "INITIATED",
    "order_uid": "8LS979579H367860S",
    "paypal_response": null
  },
  {
    "id": 280,
    "amount": "1114.80",
    "payment_status": "INITIATED",
    "order_uid": "8LS979579H367860S",
    "paypal_response": null
  },
  {
    "id": 281,
    "amount": "1114.80",
    "payment_status": "INITIATED",
    "order_uid": "9DR14264NL0943736",
    "paypal_response": null
  },
  {
    "id": 282,
    "amount": "1114.80",
    "payment_status": "INITIATED",
    "order_uid": "9DR14264NL0943736",
    "paypal_response": null
  },
  {
    "id": 283,
    "amount": "1114.80",
    "payment_status": "INITIATED",
    "order_uid": "10P323955U7406002",
    "paypal_response": null
  },
  {
    "id": 284,
    "amount": "1114.80",
    "payment_status": "INITIATED",
    "order_uid": "10P323955U7406002",
    "paypal_response": null
  },
  {
    "id": 285,
    "amount": "1114.80",
    "payment_status": "INITIATED",
    "order_uid": "3VB00121EB7395910",
    "paypal_response": null
  },
  {
    "id": 286,
    "amount": "1114.80",
    "payment_status": "INITIATED",
    "order_uid": "3VB00121EB7395910",
    "paypal_response": null
  },
  {
    "id": 287,
    "amount": "1114.80",
    "payment_status": "INITIATED",
    "order_uid": "5U036646UR687672P",
    "paypal_response": null
  },
  {
    "id": 288,
    "amount": "1114.80",
    "payment_status": "INITIATED",
    "order_uid": "5U036646UR687672P",
    "paypal_response": null
  },
  {
    "id": 289,
    "amount": "1114.80",
    "payment_status": "INITIATED",
    "order_uid": "10105316JJ833204H",
    "paypal_response": null
  },
  {
    "id": 290,
    "amount": "1114.80",
    "payment_status": "INITIATED",
    "order_uid": "10105316JJ833204H",
    "paypal_response": null
  },
  {
    "id": 291,
    "amount": "1114.80",
    "payment_status": "INITIATED",
    "order_uid": "5RD891730B8978708",
    "paypal_response": null
  },
  {
    "id": 292,
    "amount": "1114.80",
    "payment_status": "INITIATED",
    "order_uid": "5RD891730B8978708",
    "paypal_response": null
  },
  {
    "id": 293,
    "amount": "1114.80",
    "payment_status": "INITIATED",
    "order_uid": "91488751JK894940T",
    "paypal_response": null
  },
  {
    "id": 294,
    "amount": "1114.80",
    "payment_status": "INITIATED",
    "order_uid": "91488751JK894940T",
    "paypal_response": null
  },
  {
    "id": 295,
    "amount": "1114.80",
    "payment_status": "INITIATED",
    "order_uid": "4LC40732L1654205T",
    "paypal_response": null
  },
  {
    "id": 296,
    "amount": "1114.80",
    "payment_status": "INITIATED",
    "order_uid": "4LC40732L1654205T",
    "paypal_response": null
  },
  {
    "id": 297,
    "amount": "1114.80",
    "payment_status": "INITIATED",
    "order_uid": "0FS08810UM5898907",
    "paypal_response": null
  },
  {
    "id": 298,
    "amount": "1114.80",
    "payment_status": "INITIATED",
    "order_uid": "0FS08810UM5898907",
    "paypal_response": null
  },
  {
    "id": 299,
    "amount": "1114.80",
    "payment_status": "INITIATED",
    "order_uid": "9T802193YM866492H",
    "paypal_response": null
  },
  {
    "id": 300,
    "amount": "1114.80",
    "payment_status": "INITIATED",
    "order_uid": "9T802193YM866492H",
    "paypal_response": null
  },
  {
    "id": 301,
    "amount": "1114.80",
    "payment_status": "INITIATED",
    "order_uid": "0DP95855P53286421",
    "paypal_response": null
  },
  {
    "id": 302,
    "amount": "1114.80",
    "payment_status": "INITIATED",
    "order_uid": "0DP95855P53286421",
    "paypal_response": null
  },
  {
    "id": 303,
    "amount": "1021.90",
    "payment_status": "INITIATED",
    "order_uid": "80T83867FU644720F",
    "paypal_response": null
  },
  {
    "id": 304,
    "amount": "1021.90",
    "payment_status": "INITIATED",
    "order_uid": "80T83867FU644720F",
    "paypal_response": null
  },
  {
    "id": 305,
    "amount": "1021.90",
    "payment_status": "INITIATED",
    "order_uid": "0CF08939V2874834P",
    "paypal_response": null
  },
  {
    "id": 306,
    "amount": "1021.90",
    "payment_status": "INITIATED",
    "order_uid": "0CF08939V2874834P",
    "paypal_response": null
  },
  {
    "id": 309,
    "amount": "1114.80",
    "payment_status": "COMPLETED",
    "order_uid": "3NY98402GN3900118",
    "paypal_response": {
      "id": "3NY98402GN3900118",
      "links": [
        {
          "rel": "self",
          "href": "https://api.sandbox.paypal.com/v2/checkout/orders/3NY98402GN3900118",
          "method": "GET"
        }
      ],
      "payer": {
        "name": {
          "surname": "Doe",
          "given_name": "John"
        },
        "address": {
          "country_code": "US"
        },
        "payer_id": "7EB8WR2KPE4P6",
        "email_address": "sb-fdnuf39684733@personal.example.com"
      },
      "status": "COMPLETED",
      "payment_source": {
        "paypal": {
          "name": {
            "surname": "Doe",
            "given_name": "John"
          },
          "address": {
            "country_code": "US"
          },
          "account_id": "7EB8WR2KPE4P6",
          "email_address": "sb-fdnuf39684733@personal.example.com",
          "account_status": "VERIFIED"
        }
      },
      "purchase_units": [
        {
          "payments": {
            "captures": [
              {
                "id": "6SV37743LE280160T",
                "links": [
                  {
                    "rel": "self",
                    "href": "https://api.sandbox.paypal.com/v2/payments/captures/6SV37743LE280160T",
                    "method": "GET"
                  },
                  {
                    "rel": "refund",
                    "href": "https://api.sandbox.paypal.com/v2/payments/captures/6SV37743LE280160T/refund",
                    "method": "POST"
                  },
                  {
                    "rel": "up",
                    "href": "https://api.sandbox.paypal.com/v2/checkout/orders/3NY98402GN3900118",
                    "method": "GET"
                  }
                ],
                "amount": {
                  "value": "0.10",
                  "currency_code": "USD"
                },
                "status": "COMPLETED",
                "create_time": "2025-04-03T07:51:50Z",
                "update_time": "2025-04-03T07:51:50Z",
                "final_capture": true,
                "seller_protection": {
                  "status": "ELIGIBLE",
                  "dispute_categories": [
                    "ITEM_NOT_RECEIVED",
                    "UNAUTHORIZED_TRANSACTION"
                  ]
                },
                "seller_receivable_breakdown": {
                  "net_amount": {
                    "value": "0.00",
                    "currency_code": "USD"
                  },
                  "paypal_fee": {
                    "value": "0.10",
                    "currency_code": "USD"
                  },
                  "gross_amount": {
                    "value": "0.10",
                    "currency_code": "USD"
                  }
                }
              }
            ]
          },
          "shipping": {
            "name": {
              "full_name": "John Doe"
            },
            "address": {
              "postal_code": "95131",
              "admin_area_1": "CA",
              "admin_area_2": "San Jose",
              "country_code": "US",
              "address_line_1": "1 Main St"
            }
          },
          "reference_id": "default"
        }
      ]
    }
  },
  {
    "id": 310,
    "amount": "1114.80",
    "payment_status": "COMPLETED",
    "order_uid": "3NY98402GN3900118",
    "paypal_response": {
      "id": "3NY98402GN3900118",
      "links": [
        {
          "rel": "self",
          "href": "https://api.sandbox.paypal.com/v2/checkout/orders/3NY98402GN3900118",
          "method": "GET"
        }
      ],
      "payer": {
        "name": {
          "surname": "Doe",
          "given_name": "John"
        },
        "address": {
          "country_code": "US"
        },
        "payer_id": "7EB8WR2KPE4P6",
        "email_address": "sb-fdnuf39684733@personal.example.com"
      },
      "status": "COMPLETED",
      "payment_source": {
        "paypal": {
          "name": {
            "surname": "Doe",
            "given_name": "John"
          },
          "address": {
            "country_code": "US"
          },
          "account_id": "7EB8WR2KPE4P6",
          "email_address": "sb-fdnuf39684733@personal.example.com",
          "account_status": "VERIFIED"
        }
      },
      "purchase_units": [
        {
          "payments": {
            "captures": [
              {
                "id": "6SV37743LE280160T",
                "links": [
                  {
                    "rel": "self",
                    "href": "https://api.sandbox.paypal.com/v2/payments/captures/6SV37743LE280160T",
                    "method": "GET"
                  },
                  {
                    "rel": "refund",
                    "href": "https://api.sandbox.paypal.com/v2/payments/captures/6SV37743LE280160T/refund",
                    "method": "POST"
                  },
                  {
                    "rel": "up",
                    "href": "https://api.sandbox.paypal.com/v2/checkout/orders/3NY98402GN3900118",
                    "method": "GET"
                  }
                ],
                "amount": {
                  "value": "0.10",
                  "currency_code": "USD"
                },
                "status": "COMPLETED",
                "create_time": "2025-04-03T07:51:50Z",
                "update_time": "2025-04-03T07:51:50Z",
                "final_capture": true,
                "seller_protection": {
                  "status": "ELIGIBLE",
                  "dispute_categories": [
                    "ITEM_NOT_RECEIVED",
                    "UNAUTHORIZED_TRANSACTION"
                  ]
                },
                "seller_receivable_breakdown": {
                  "net_amount": {
                    "value": "0.00",
                    "currency_code": "USD"
                  },
                  "paypal_fee": {
                    "value": "0.10",
                    "currency_code": "USD"
                  },
                  "gross_amount": {
                    "value": "0.10",
                    "currency_code": "USD"
                  }
                }
              }
            ]
          },
          "shipping": {
            "name": {
              "full_name": "John Doe"
            },
            "address": {
              "postal_code": "95131",
              "admin_area_1": "CA",
              "admin_area_2": "San Jose",
              "country_code": "US",
              "address_line_1": "1 Main St"
            }
          },
          "reference_id": "default"
        }
      ]
    }
  },
  {
    "id": 311,
    "amount": "0.00",
    "payment_status": "INITIATED",
    "order_uid": "1SG73573R5840363M",
    "paypal_response": null
  },
  {
    "id": 312,
    "amount": "0.00",
    "payment_status": "INITIATED",
    "order_uid": "1SG73573R5840363M",
    "paypal_response": null
  },
  {
    "id": 313,
    "amount": "0.00",
    "payment_status": "INITIATED",
    "order_uid": "3ST80133HN101903R",
    "paypal_response": null
  },
  {
    "id": 314,
    "amount": "0.00",
    "payment_status": "INITIATED",
    "order_uid": "3ST80133HN101903R",
    "paypal_response": null
  },
  {
    "id": 315,
    "amount": "153.60",
    "payment_status": "INITIATED",
    "order_uid": "0SN6806982805562V",
    "paypal_response": null
  },
  {
    "id": 316,
    "amount": "153.60",
    "payment_status": "INITIATED",
    "order_uid": "0SN6806982805562V",
    "paypal_response": null
  },
  {
    "id": 317,
    "amount": "153.60",
    "payment_status": "INITIATED",
    "order_uid": "8SV80800KT733580K",
    "paypal_response": null
  },
  {
    "id": 318,
    "amount": "153.60",
    "payment_status": "INITIATED",
    "order_uid": "8SV80800KT733580K",
    "paypal_response": null
  }
]