[
  {
    "id": 189,
    "wishlist_id": 138,
    "user_id": 11,
    "wishlist_ord": 1
  },
  {
    "id": 190,
    "wishlist_id": 139,
    "user_id": 11,
    "wishlist_ord": 2
  },
  {
    "id": 193,
    "wishlist_id": 142,
    "user_id": 17,
    "wishlist_ord": 1
  },
  {
    "id": 194,
    "wishlist_id": 143,
    "user_id": 17,
    "wishlist_ord": 2
  },
  {
    "id": 199,
    "wishlist_id": 148,
    "user_id": 11,
    "wishlist_ord": 3
  },
  {
    "id": 200,
    "wishlist_id": 149,
    "user_id": 11,
    "wishlist_ord": 4
  },
  {
    "id": 201,
    "wishlist_id": 150,
    "user_id": 11,
    "wishlist_ord": 5
  },
  {
    "id": 202,
    "wishlist_id": 151,
    "user_id": 11,
    "wishlist_ord": 6
  },
  {
    "id": 203,
    "wishlist_id": 152,
    "user_id": 11,
    "wishlist_ord": 7
  },
  {
    "id": 204,
    "wishlist_id": 153,
    "user_id": 11,
    "wishlist_ord": 8
  },
  {
    "id": 207,
    "wishlist_id": 156,
    "user_id": 17,
    "wishlist_ord": 3
  },
  {
    "id": 208,
    "wishlist_id": 157,
    "user_id": 17,
    "wishlist_ord": 4
  },
  {
    "id": 209,
    "wishlist_id": 158,
    "user_id": 17,
    "wishlist_ord": 5
  },
  {
    "id": 210,
    "wishlist_id": 159,
    "user_id": 17,
    "wishlist_ord": 6
  }
]